withings2intervals/__init__.py
withings2intervals/config_example.ini
withings2intervals/withings2intervals.py
withings2intervals-0.1.4.dist-info/METADATA
withings2intervals-0.1.4.dist-info/WHEEL
withings2intervals-0.1.4.dist-info/entry_points.txt
withings2intervals-0.1.4.dist-info/RECORD
