Metadata-Version: 2.1
Name: withings2intervals
Version: 0.1.4
Summary: Sync Withings data to Intervals.icu
Author: Stefano Mosconi
Author-email: stefano.mosconi@gmail.com
Requires-Python: >=3.12,<4.0
Classifier: Programming Language :: Python :: 3
Classifier: Programming Language :: Python :: 3.12
Classifier: Programming Language :: Python :: 3.13
Requires-Dist: colorama (>=0.4.6,<0.5.0)
Requires-Dist: requests (>=2.32.3,<3.0.0)
